LICENSE
MANIFEST.in
README.md
setup.py
simple_sqlite/__init__.py
simple_sqlite/simple_sqlite.py
simple_sqlite.egg-info/PKG-INFO
simple_sqlite.egg-info/SOURCES.txt
simple_sqlite.egg-info/dependency_links.txt
simple_sqlite.egg-info/top_level.txt
simple_sqlite/util/__init__.py
simple_sqlite/util/logger.py