Metadata-Version: 2.1
Name: simple-sqlite
Version: 2.1.1
Summary: This package can help you using sqlite3 library much easier and faster.
Home-page: https://github.com/Svinokur/simple_sqlite
Author: Stanislav Vinokur
Author-email: stasvinokur@yahoo.com
License: MIT
Keywords: sqlite,sqlite3
Platform: UNKNOWN
Classifier: Development Status :: 5 - Production/Stable
Classifier: Operating System :: Microsoft :: Windows :: Windows 10
Classifier: License :: OSI Approved :: MIT License
Classifier: Programming Language :: Python :: 3
License-File: LICENSE
